{
  "lang": "en",
  "appName": "AudioEdit",
  "appTagline": "Single-track web audio editor",

  "menu": {
    "newProject": "New project",
    "openProject": "Open project (.aed.zip)",
    "saveProject": "Save project (.aed.zip)",
    "exportAudio": "Export result",
    "language": "Language"
  },

  "projectInfo": {
    "title": "Project info",
    "totalDuration": "Total duration",
    "regionCount": "Region count",
    "totalSize": "Total audio size",
    "zipSize": "ZIP size",
    "unknown": "unknown",
    "noRegions": "No regions",
    "projectName": "Project name"
  },

  "transport": {
    "title": "Playback",
    "playAll": "Play entire project",
    "stop": "Stop playback",
    "rewind5s": "Rewind 5 seconds",
    "rewind10s": "Rewind 10 seconds",
    "rewind30s": "Rewind 30 seconds",
    "rewind1m": "Rewind 1 minute",
    "rewind5m": "Rewind 5 minutes",
    "forward5s": "Forward 5 seconds",
    "forward10s": "Forward 10 seconds",
    "forward30s": "Forward 30 seconds",
    "forward1m": "Forward 1 minute",
    "forward5m": "Forward 5 minutes",
    "currentPosition": "Current position",
    "rewindGroup": "Rewind",
    "forwardGroup": "Fast forward"
  },

  "regions": {
    "title": "Regions",
    "addRegion": "Load audio file as new region",
    "noRegions": "No regions yet. Load an audio file.",
    "regionLabel": "Region",
    "start": "Start",
    "end": "End",
    "duration": "Duration",
    "notes": "Notes",
    "notesPlaceholder": "Region notes…",
    "regionName": "Region name",
    "playRegion": "Play region",
    "playFromRegion": "Play from this region to end",
    "splitRegion": "Split region at current position",
    "mergeWithPrevious": "Merge with previous region",
    "insertAfter": "Insert audio file after this region",
    "removeRegion": "Remove region",
    "moveUp": "Move region up",
    "moveDown": "Move region down",
    "order": "Order",
    "confirmRemove": "Really remove region \"{name}\"?",
    "confirmNew": "Really create a new project? Unsaved changes will be lost.",
    "nameExists": "A region named \"{name}\" already exists. Please choose another name.",
    "cannotMergeFirst": "The first region cannot be merged with a previous one.",
    "splitNoPosition": "Playback must be active or set a playback position inside the region.",
    "splitAtEdge": "Cannot split at the very beginning or end of a region.",
    "positionOutside": "Current position is not inside this region."
  },

  "export": {
    "title": "Export result",
    "format": "Output format",
    "wav": "WAV (lossless)",
    "mp3": "MP3 (lossy)",
    "ogg": "OGG Vorbis (lossy)",
    "m4a": "M4A / AAC (lossy)",
    "quality": "Quality / bitrate",
    "exportBtn": "Export",
    "cancel": "Cancel",
    "processing": "Processing…",
    "progress": "Export progress",
    "done": "Export complete",
    "errorNoRegions": "Cannot export – project has no regions.",
    "errorExport": "Export error: {msg}",
    "mixingRegions": "Mixing region {current} of {total}…",
    "encoding": "Encoding output…",
    "saving": "Saving file…",
    "m4aNotSupported": "M4A export is not supported in this browser. Try WAV or MP3."
  },

  "status": {
    "ready": "Ready",
    "loading": "Loading…",
    "saving": "Saving project…",
    "saved": "Project saved",
    "opened": "Project opened",
    "newProject": "New project created",
    "regionAdded": "Region \"{name}\" added",
    "regionRemoved": "Region \"{name}\" removed",
    "regionSplit": "Region split",
    "regionsMerged": "Regions merged",
    "regionMoved": "Region moved",
    "error": "Error: {msg}",
    "playing": "Playing",
    "stopped": "Stopped",
    "exportDone": "Export complete: {file}"
  },

  "dialog": {
    "ok": "OK",
    "cancel": "Cancel",
    "confirm": "Confirm",
    "close": "Close"
  },

  "formats": {
    "seconds": "s",
    "minutes": "min",
    "bytes": "B",
    "kilobytes": "kB",
    "megabytes": "MB"
  }
}
